Workbook
Name NativeTimeline_Order_Date: #N/A
Name Slicer_Category: #N/A
Name Slicer_Region: #N/A

Sheet Raw Data
A1: Row ID | B1: Order ID | C1: Order Date | D1: Ship Date | E1: Ship Mode | F1: Customer ID | G1: Customer Name | H1: Segment | I1: Country | J1: City | K1: State | L1: Region | M1: Postal Code | N1: Product ID | O1: Category | P1: Sub-Category | Q1: Product Name | R1: Sales | S1: Quantity | T1: Discount | U1: Profit | W1: =$U$1 -> Profit
A2: 1595 | B2: ORD-2024-00595 | C2: 45334 | D2: 45339 | E2: Standard Class | F2: CUST-1089 | G2: Nikhil Varma | H2: Corporate | I2: India | J2: Bhubaneswar | K2: Odisha | L2: East | M2: 682001 | N2: P-235 | O2: Clothing | P2: Shirts | Q2: Cotton Casual Shirt | R2: 2439.75 | S2: 2 | T2: 0.1 | U2: 498.33 | W2: =$U$1 -> Profit
A3: 1098 | B3: ORD-2024-00098 | C3: 45577 | D3: 45580 | E3: Standard Class | F3: CUST-1102 | G3: Amal Thomas | H3: Consumer | I3: India | J3: Ahmedabad | K3: Gujarat | L3: South | M3: 695001 | N3: P-649 | O3: Electronics | P3: Mobiles | Q3: Samsung Galaxy A55 | R3: 184132.26 | S3: 7 | T3: 0.25 | U3: -8938.1 | W3: =$U$1 -> Profit
A4: 1282 | B4: ORD-2024-00282 | C4: 45480 | D4: 45482 | E4: First Class | F4: CUST-1099 | G4: Ananya Menon | H4: Consumer | I4: India | J4: Delhi | K4: Delhi | L4: south | M4: 682001 | N4: P-858 | O4: Furniture | P4: Tables | Q4: Study Table | R4: 32210.22 | S4: 5 | T4: 0.05 | U4: 3109.97 | W4: =$U$1 -> Profit
A5: 1658 | B5: ORD-2024-00658 | C5: 45508 | D5: 45514 | E5: Standard Class | F5: CUST-1026 | G5: Rahul Kumar | H5: Consumer | I5: India | J5: Hyderabad | K5: Telangana | L5: North | M5: 682001 | N5: P-129 | O5: Furniture | P5: Chairs | Q5: Ergonomic Office Chair | R5: 18979.09 | S5: 3 | T5: 0.25 | U5: -50.85 | W5: =$U$1 -> Profit
A6: 1586 | B6: ORD-2024-00586 | C6: 45546 | D6: 45548 | E6: Second Class | F6: CUST-1086 | G6: Muhammed Shafi | H6: Corporate | I6: India | J6: Bengaluru | K6: Karnataka | L6: South | M6: 673001 | N6: P-760 | O6: Electronics | P6: Mobiles | Q6: Samsung Galaxy A55 | R6: 102685.8 | S6: 25 | T6: 0.3 | U6: -10828.26
A7: 1079 | B7: ORD-2024-00079 | C7: 45396 | D7: 45399 | E7: Second Class | F7: CUST-1119 | G7: Arjun Das | H7: Consumer | I7: India | J7: Jaipur | K7: Rajasthan | L7: East | M7: 400001 | N7: P-596 | O7: Clothing | P7: Shoes | Q7: Running Shoes | R7: 6576.27 | S7: 2 | T7: 0 | U7: 1859.13
A8: 1055 | B8: ORD-2024-00055 | C8: 45480 | D8: 45482 | E8: Standard Class | F8: CUST-1100 | G8: Riya Paul | H8: corporate | I8: India | J8: Lucknow | K8: Uttar Pradesh | L8: West | M8: 695001 | N8: P-210 | O8: electronics | P8: Mobiles | Q8: Samsung Galaxy A55 | R8: 29272.2 | S8: 1 | T8: 0.15 | U8: 288.51
A9: 1110 | B9: ORD-2024-00110 | C9: 45329 | D9: 45330 | E9: First Class | F9: CUST-1078 | G9: Rahul Kumar | H9: Consumer | I9: India | J9: Hyderabad | K9: Telangana | L9: south | M9: 682001 | N9: P-381 | O9: Furniture | P9: Bookcases | Q9: Wooden Bookshelf | R9: 4587.26 | S9: 1 | T9: 0.3 | U9: -188.59
A10: 1325 | B10: ORD-2024-00325 | C10: 45298 | D10: 45304 | E10: Same Day | F10: CUST-1015 | G10: Amal Thomas | H10: Corporate | I10: India | J10: Delhi | K10: Delhi | L10: west | M10: 682001 | N10: P-680 | O10: Furniture | P10: Bookcases | Q10: Wooden Bookshelf | R10: 23436.39 | S10: 5 | T10: 0.3 | U10: -819.63 | W10: Running Shoes
A11: 1502 | B11: ORD-2024-00502 | C11: 45405 | D11: 45411 | E11: Second Class | F11: CUST-1097 | G11: Fathima Ali | H11: Home Office | I11: India | J11: Pune | K11: Maharashtra | L11: South | M11: 682001 | N11: P-549 | O11: Clothing | P11: Shoes | Q11: Running Shoes | R11: 15259.27 | S11: 6 | T11: 0.25 | U11: 1490.22 | W11: =_xlfn.XLOOKUP(Q7,Q:Q,N:N) -> P-596
A12: 1040 | B12: ORD-2024-00040 | C12: 45638 | D12: 45644 | E12: Second Class | F12: CUST-1079 | G12: Diya Mathew | H12: Consumer | I12: India | J12: Chennai | K12: Tamil Nadu | L12: North | M12: 560001 | N12: P-661 | O12: office supplies | P12: Binders | Q12: Office Binder Pack | R12: 952.92 | S12: 2 | T12: 0.25 | U12: 28.87
A13: 1665 | B13: ORD-2024-00665 | C13: 45421 | D13: 45426 | E13: Same Day | F13: CUST-1040 | G13: Adil Khan | H13: home office | I13: India | J13: Lucknow | K13: Uttar Pradesh | L13: North | M13: 110001 | N13: P-801 | O13: Clothing | P13: Shoes | Q13: Running Shoes | R13: 11812.53 | S13: 4 | T13: 0.1 | U13: 2183.35
A14: 1540 | B14: ORD-2024-00540 | C14: 45514 | D14: 45519 | E14: First Class | F14: CUST-1070 | G14: Nikhil Varma | H14: Consumer | I14: India | J14: Kochi | K14: Kerala | L14: West | M14: 682001 | N14: P-778 | O14: Furniture | P14: Tables | Q14: Study Table | R14: 20626.29 | S14: 4 | T14: 0.25 | U14: -63.17
A15: 1640 | B15: ORD-2024-00640 | C15: 45474 | D15: 45478 | E15: Same Day | F15: CUST-1063 | G15: Vishnu Raj | H15: Corporate | I15: India | J15: Bhubaneswar | K15: Odisha | L15: North | M15: 682001 | N15: P-886 | O15: Office Supplies | P15: Storage | Q15: Document Organizer | R15: 2686.98 | S15: 4 | T15: 0.25 | U15: 100.71
A16: 1600 | B16: ORD-2024-00600 | C16: 45381 | D16: 45387 | E16: Standard Class | F16: CUST-1072 | G16: Nikhil Varma | H16: Consumer | I16: India | J16: Pune | K16: Maharashtra | L16: west | M16: 682001 | N16: P-442 | O16: furniture | P16: Tables | Q16: Study Table | R16: 5990.08 | S16: 1 | T16: 0.2 | U16: 146.47
A17: 1335 | B17: ORD-2024-00335 | C17: 45534 | D17: 45536 | E17: Second Class | F17: CUST-1077 | G17: Asha Krishnan | H17: Consumer | I17: India | J17: Pune | K17: Maharashtra | L17: South | M17: 682001 | N17: P-358 | O17: Office Supplies | P17: Binders | Q17: Office Binder Pack | R17: 3087.01 | S17: 5 | T17: 0 | U17: 551.06
A18: 1255 | B18: ORD-2024-00255 | C18: 45334 | D18: 45339 | E18: Standard Class | F18: CUST-1102 | G18: Asha Krishnan | H18: Corporate | I18: India | J18: Ahmedabad | K18: Gujarat | L18: West | M18: 695001 | N18: P-133 | O18: Furniture | P18: Bookcases | Q18: Wooden Bookshelf | R18: 13035.13 | S18: 2 | T18: 0.05 | U18: 1849.55
A19: 1638 | B19: ORD-2024-00638 | C19: 45647 | D19: 45652 | E19: Standard Class | F19: CUST-1095 | G19: Muhammed Shafi | H19: consumer | I19: India | J19: Lucknow | K19: Uttar Pradesh | L19: West | M19: 673001 | N19: P-472 | O19: Office Supplies | P19: Art | Q19: Marker Set | R19: 284.11 | S19: 1 | T19: 0.25 | U19: 8.55
A20: 1219 | B20: ORD-2024-00219 | C20: 45560 | D20: 45561 | E20: Standard Class | F20: CUST-1105 | G20: Adil Khan | H20: Consumer | I20: India | J20: Kolkata | K20: West Bengal | L20: South | M20: 110001 | N20: P-106 | O20: Office Supplies | P20: Binders | Q20: Office Binder Pack | R20: 3633.4 | S20: 6 | T20: 0 | U20: 843.62
A21: 1537 | B21: ORD-2024-00537 | C21: 45524 | D21: 45528 | E21: Standard Class | F21: CUST-1009 | G21: Sneha Nair | H21: Home Office | I21: India | J21: Thiruvananthapuram | K21: Kerala | L21: South | M21: 695001 | N21: P-590 | O21: Clothing | P21: Shirts | Q21: Cotton Casual Shirt | R21: 2075.89 | S21: 2 | T21: 0.2 | U21: 189.06
A22: 1351 | B22: ORD-2024-00351 | C22: 45484 | D22: 45490 | E22: First Class | F22: CUST-1099 | G22: Vishnu Raj | H22: Consumer | I22: India | J22: Thiruvananthapuram | K22: Kerala | L22: SOUTH | M22: 600001 | N22: P-149 | O22: Electronics | P22: Mobiles | Q22: Samsung Galaxy A55 | R22: 144750.86 | S22: 4 | T22: 0 | U22: 12354.53
A23: 1723 | B23: ORD-2024-00723 | C23: 45485 | D23: 45490 | E23: Second Class | F23: CUST-1014 | G23: Meera Joseph | H23: Corporate | I23: India | J23: Chennai | K23: Tamil Nadu | L23: West | M23: 110001 | N23: P-897 | O23: Office Supplies | P23: Art | Q23: Marker Set | R23: 1529.06 | S23: 4 | T23: 0.05 | U23: 214.77
... A25: 1287 | B25: ORD-2024-00287 | C25: 45571 | D25: 45573 | E25: Second Class | F25: CUST-1001 | G25: Muhammed Shafi | H25: Consumer | I25: India | J25: Bengaluru | K25: Karnataka | L25: East | M25: 673001 | N25: P-338 | O25: Office Supplies | P25: Paper | Q25: A4 Copier Paper | R25: 3186.37 | S25: 8 | T25: 0.1 | U25: 456.42
A26: 1592 | B26: ORD-2024-00592 | C26: 45587 | D26: 45592 | E26: Second Class | F26: CUST-1012 | G26: Amal Thomas | H26: Consumer | I26: India | J26: Bengaluru | K26: Karnataka | L26: east | M26: 110001 | N26: P-321 | O26: Home Appliances | P26: Kitchen | Q26: Mixer Grinder | R26: 5626.92 | S26: 1 | T26: 0.05
A27: 1435 | B27: ORD-2024-00435 | C27: 45493 | D27: 45499 | E27: Second Class | F27: CUST-1059 | G27: Ananya Menon | H27: Consumer | I27: India | J27: Bhubaneswar | K27: Odisha | L27: East | M27: 695001 | N27: P-805 | O27: Furniture | P27: Bookcases | Q27: Wooden Bookshelf | R27: 16249.12 | S27: 3 | T27: 0.2 | U27: 596.21
A28: 1382 | B28: ORD-2024-00382 | C28: 45576 | D28: 45579 | E28: Second Class | F28: CUST-1021 | G28: Diya Mathew | H28: Consumer | I28: India | J28: Kolkata | K28: West Bengal | L28: North | M28: 673001 | N28: P-438 | O28: Office Supplies | P28: Binders | Q28: Office Binder Pack | R28: 530.27 | S28: 1 | T28: 0.15 | U28: 60.98
A29: 1369 | B29: ORD-2024-00369 | C29: 45473 | D29: 45479 | E29: First Class | F29: CUST-1071 | G29: Vishnu Raj | H29: Corporate | I29: India | J29: Kochi | K29: Kerala | L29: North | M29: 400001 | N29: P-208 | O29: Electronics | P29: Mobiles | Q29: Samsung Galaxy A55 | R29: 28304.39 | S29: 1 | T29: 0.2 | U29: -655.7
A30: 1702 | B30: ORD-2024-00702 | C30: 45522 | D30: 45527 | E30: Second Class | F30: CUST-1026 | G30: Arjun Das | H30: consumer | I30: India | J30: Kolkata | K30: West Bengal | L30: East | M30: 673001 | N30: P-441 | O30: Clothing | P30: Shirts | Q30: Cotton Casual Shirt | R30: 3888.64 | S30: 3 | T30: 0 | U30: 1087.07
A31: 1175 | B31: ORD-2024-00175 | C31: 45318 | D31: 45323 | E31: Second Class | F31: CUST-1047 | G31: Vishnu Raj | H31: corporate | I31: India | J31: Kolkata | K31: West Bengal | L31: North | M31: 673001 | N31: P-495 | O31: Furniture | P31: Tables | Q31: Study Table | R31: 10583.33 | S31: 2 | T31: 0.25 | U31: -28.12
A32: 1471 | B32: ORD-2024-00471 | C32: 45332 | D32: 45336 | E32: Standard Class | F32: CUST-1047 | G32: Vishnu Raj | H32: Home Office | I32: India | J32: Kochi | K32: Kerala | L32: east | M32: 110001 | N32: P-477 | O32: Electronics | P32: Laptops | Q32: Dell Inspiron 15 | R32: 35084.1 | S32: 1 | T32: 0.3 | U32: -3062.93
A33: 1581 | B33: ORD-2024-00581 | C33: 45504 | D33: 45506 | E33: First Class | F33: CUST-1071 | G33: Rahul Kumar | H33: Consumer | I33: India | J33: Jaipur | K33: Rajasthan | L33: East | M33: 682001 | N33: P-695 | O33: Electronics | P33: Accessories | Q33: Logitech Wireless Mouse | R33: 1199.43 | S33: 1 | T33: 0.05 | U33: 75.71
A34: 1156 | B34: ORD-2024-00156 | C34: 45471 | D34: 45475 | E34: Standard Class | F34: CUST-1094 | G34: Riya Paul | H34: Corporate | I34: India | J34: Chennai | K34: Tamil Nadu | L34: north | M34: 600001 | N34: P-545 | O34: Office Supplies | P34: Paper | Q34: A4 Copier Paper | R34: 623.85 | S34: 2 | T34: 0.3 | U34: 2.46
A35: 1121 | B35: ORD-2024-00121 | C35: 45315 | D35: 45317 | E35: Same Day | F35: CUST-1077 | G35: Aarav Nair | H35: Corporate | I35: India | J35: Kochi | K35: Kerala | L35: SOUTH | M35: 682001 | N35: P-408 | O35: Furniture | P35: Chairs | Q35: Ergonomic Office Chair | R35: 23202.51 | S35: 3 | T35: 0.15 | U35: 1779.29
A36: 1353 | B36: ORD-2024-00353 | C36: 45507 | D36: 45513 | E36: Standard Class | F36: CUST-1085 | G36: Vishnu Raj | H36: Corporate | I36: India | J36: Thiruvananthapuram | K36: Kerala | L36: North | M36: 600001 | N36: P-720 | O36: Electronics | P36: Accessories | Q36: HP Wireless Keyboard | R36: 4269.34 | S36: 3 | T36: 0.15 | U36: 66.44
A37: 1399 | B37: ORD-2024-00399 | C37: 45452 | D37: 45454 | E37: Second Class | F37: CUST-1092 | G37: Nikhil Varma | H37: Consumer | I37: India | J37: Mumbai | K37: Maharashtra | L37: East | M37: 695001 | N37: P-960 | O37: Clothing | P37: Shoes | Q37: Running Shoes | R37: 6842.49 | S37: 2 | T37: 0 | U37: 1766.33
A38: 1232 | B38: ORD-2024-00232 | C38: 45521 | D38: 45526 | E38: Same Day | F38: CUST-1014 | G38: Aarav Nair | H38: Consumer | I38: India | J38: Bhubaneswar | K38: Odisha | L38: South | M38: 695001 | N38: P-667 | O38: Furniture | P38: Chairs | Q38: Ergonomic Office Chair | R38: 6625.97 | S38: 1 | T38: 0.25 | U38: -17.26
A39: 1716 | B39: ORD-2024-00716 | C39: 45335 | D39: 45338 | E39: First Class | F39: CUST-1052 | G39: Asha Krishnan | H39: Consumer | I39: India | J39: Thiruvananthapuram | K39: Kerala | L39: West | M39: 560001 | N39: P-162 | O39: Clothing | P39: Shoes | Q39: Running Shoes | R39: 15884.13 | S39: 5 | T39: 0 | U39: 4002
A40: 1683 | B40: ORD-2024-00683 | C40: 45375 | D40: 45381 | E40: Same Day | F40: CUST-1056 | G40: Ananya Menon | H40: Consumer | I40: India | J40: Thiruvananthapuram | K40: Kerala | L40: east | M40: 673001 | N40: P-552 | P40: Laptops | Q40: Dell Inspiron 15 | R40: 45848.58 | S40: 1 | T40: 0.15 | U40: 467.53
A41: 1686 | B41: ORD-2024-00686 | C41: 45640 | D41: 45646 | E41: Standard Class | F41: CUST-1051 | G41: Meera Joseph | H41: Consumer | I41: India | J41: Ahmedabad | K41: Gujarat | L41: South | M41: 110001 | N41: P-431 | O41: Office supplies | P41: Art | Q41: Marker Set | R41: 694.72 | S41: 2 | T41: 0.15 | U41: 59.85
A42: 1423 | B42: ORD-2024-00423 | C42: 45603 | D42: 45604 | E42: Same Day | F42: CUST-1120 | G42: Amal Thomas | H42: Consumer | I42: India | J42: Pune | K42: Maharashtra | L42: North | M42: 400001 | N42: P-711 | O42: Electronics | P42: Mobiles | Q42: Samsung Galaxy A55 | R42: 33976.3 | S42: 1 | T42: 0 | U42: 3577.85
A43: 1372 | B43: ORD-2024-00372 | C43: 45575 | D43: 45579 | E43: Same Day | F43: CUST-1119 | G43: Vishnu Raj | H43: Consumer | I43: India | J43: Jaipur | K43: Rajasthan | L43: West | M43: 400001 | N43: P-692 | O43: Office Supplies | P43: Binders | Q43: Office Binder Pack | R43: 2027.25 | S43: 3 | T43: 0 | U43: 406
A44: 1067 | B44: ORD-2024-00067 | C44: 45421 | D44: 45425 | E44: Standard Class | F44: CUST-1106 | G44: Ananya Menon | H44: Consumer | I44: India | J44: Ahmedabad | K44: Gujarat | L44: East | M44: 560001 | N44: P-175 | O44: Office Supplies | P44: Paper | Q44: A4 Copier Paper | R44: 422.63 | S44: 1 | T44: 0 | U44: 77.66
A45: 1291 | B45: ORD-2024-00291 | C45: 45441 | D45: 45444 | E45: First Class | F45: CUST-1119 | G45: Asha Krishnan | H45: Consumer | I45: India | J45: Jaipur | K45: Rajasthan | L45: East | M45: 400001 | N45: P-951 | O45: Electronics | P45: Laptops | Q45: Dell Inspiron 15 | R45: 325458.06 | S45: 7 | T45: 0.1 | U45: 18160.8
A46: 1745 | B46: ORD-2024-00745 | C46: 45466 | D46: 45468 | E46: Same Day | F46: CUST-1077 | G46: Meera Joseph | H46: Consumer | I46: India | J46: Bhubaneswar | K46: Odisha | L46: South | M46: 400001 | N46: P-236 | O46: Clothing | P46: Shirts | Q46: Cotton Casual Shirt | R46: 1100.03 | S46: 1 | T46: 0.2 | U46: 128.62
A47: 1473 | B47: ORD-2024-00473 | C47: 45583 | D47: 45589 | E47: Second Class | F47: CUST-1072 | G47: Nikhil Varma | H47: Consumer | I47: India | J47: Bengaluru | K47: Karnataka | L47: East | M47: 400001 | N47: P-208 | O47: Office Supplies | P47: Binders | Q47: Office Binder Pack | R47: 557.52 | S47: 1 | T47: 0.1 | U47: 56.86
A48: 1725 | B48: ORD-2024-00725 | C48: 45427 | D48: 45432 | E48: Same Day | F48: CUST-1082 | G48: Amal Thomas | H48: Consumer | I48: India | J48: Ahmedabad | K48: Gujarat | L48: East | M48: 400001 | N48: P-601 | O48: Electronics | P48: Mobiles | Q48: Samsung Galaxy A55 | R48: 86762.2 | S48: 3 | T48: 0.25 | U48: -4972.36
A49: 1200 | B49: ORD-2024-00200 | C49: 45524 | D49: 45526 | E49: Same Day | F49: CUST-1059 | G49: Diya Mathew | H49: Home Office | I49: India | J49: Ahmedabad | K49: Gujarat | L49: South | M49: 600001 | N49: P-573 | O49: Electronics | P49: Mobiles | Q49: Samsung Galaxy A55 | R49: 74890.03 | S49: 2 | T49: 0 | U49: 9286.35
A50: 1609 | B50: ORD-2024-00609 | C50: 45468 | D50: 45470 | E50: First Class | F50: CUST-1058 | G50: Vishnu Raj | H50: Consumer | I50: India | J50: Mumbai | K50: Maharashtra | L50: West | M50: 600001 | N50: P-408 | O50: Electronics | P50: Accessories | Q50: Logitech Wireless Mouse | R50: 3583.41 | S50: 4 | T50: 0.2 | U50: -78.14
A51: 1233 | B51: ORD-2024-00233 | C51: 45298 | D51: 45301 | E51: Same Day | F51: CUST-1050 | G51: Asha Krishnan | H51: Corporate | I51: India | J51: Kochi | K51: Kerala | L51: South | M51: 400001 | N51: P-672 | O51: Office Supplies | P51: Storage | Q51: Document Organizer | R51: 1530.38 | S51: 2 | T51: 0.25 | U51: 53.8
A52: 1034 | B52: ORD-2024-00034 | C52: 45462 | D52: 45466 | E52: Second Class | F52: CUST-1035 | G52: Rahul Kumar | H52: Consumer | I52: India | J52: Bhubaneswar | K52: Odisha | L52: South | M52: 560001 | N52: P-993 | O52: Clothing | P52: Shoes | Q52: Running Shoes | R52: 5730.69 | S52: 2 | T52: 0.05 | U52: 1434.76
A53: 1606 | B53: ORD-2024-00606 | C53: 45526 | D53: 45529 | E53: Second Class | F53: CUST-1115 | G53: Asha Krishnan | H53: Corporate | I53: India | J53: Mumbai | K53: Maharashtra | L53: north | M53: 682001 | N53: P-908 | O53: Office Supplies | P53: Art | Q53: Marker Set | R53: 525.72 | S53: 2 | T53: 0.3 | U53: 2.56
A54: 1078 | B54: ORD-2024-00078 | C54: 45628 | D54: 45633 | E54: Same Day | F54: CUST-1053 | G54: Aarav Nair | H54: Home Office | I54: India | J54: Bhubaneswar | K54: Odisha | M54: 600001 | N54: P-470 | O54: Furniture | P54: Bookcases | Q54: Wooden Bookshelf | R54: 34486.53 | S54: 5 | T54: 0 | U54: 4806.2
A55: 1659 | B55: ORD-2024-00659 | C55: 45621 | D55: 45622 | E55: Same Day | F55: CUST-1101 | G55: Aarav Nair | H55: Corporate | I55: India | J55: Chennai | K55: Tamil Nadu | L55: South | M55: 110001 | N55: P-185 | O55: Clothing | P55: Shoes | Q55: Running Shoes | R55: 12211.37 | S55: 4 | T55: 0.05 | U55: 2963.52
A56: 1182 | B56: ORD-2024-00182 | C56: 45323 | D56: 45329 | E56: Second Class | F56: CUST-1067 | G56: Fathima Ali | H56: consumer | I56: India | J56: Bengaluru | K56: Karnataka | L56: North | M56: 400001 | N56: P-589 | O56: Furniture | P56: Bookcases | Q56: Wooden Bookshelf | R56: 13350.23 | S56: 3 | T56: 0.3 | U56: -477.92
A57: 1480 | B57: ORD-2024-00480 | C57: 45596 | D57: 45602 | E57: First Class | F57: CUST-1005 | G57: Nikhil Varma | H57: Corporate | I57: India | J57: Thiruvananthapuram | K57: Kerala | L57: East | M57: 673001 | N57: P-898 | O57: Office Supplies | P57: Paper | Q57: A4 Copier Paper | R57: 1703.89 | S57: 4 | T57: 0 | U57: 381.34
A58: 1211 | B58: ORD-2024-00211 | C58: 45505 | D58: 45510 | E58: Second Class | F58: CUST-1050 | G58: Fathima Ali | H58: Corporate | I58: India | J58: Kolkata | K58: West Bengal | L58: North | M58: 682001 | N58: P-438 | O58: electronics | P58: Accessories | Q58: Logitech Wireless Mouse | R58: 5651.92 | S58: 6 | T58: 0.25 | U58: -339.69
A59: 1551 | B59: ORD-2024-00551 | C59: 45571 | D59: 45576 | E59: First Class | F59: CUST-1005 | G59: Aarav Nair | H59: Consumer | I59: India | J59: Hyderabad | K59: Telangana | L59: East | M59: 400001 | N59: P-477 | O59: Clothing | P59: Shirts | Q59: Cotton Casual Shirt | R59: 2927.15 | S59: 3 | T59: 0.25 | U59: 316.2
A60: 1677 | B60: ORD-2024-00677 | C60: 45590 | D60: 45596 | E60: Same Day | F60: CUST-1011 | G60: Aarav Nair | H60: Corporate | I60: India | J60: Chennai | K60: Tamil Nadu | L60: East | M60: 682001 | N60: P-992 | O60: Electronics | P60: Accessories | Q60: HP Wireless Keyboard | R60: 8555.14 | S60: 6 | T60: 0.2 | U60: -190.37
A61: 1011 | B61: ORD-2024-00011 | C61: 45487 | D61: 45492 | E61: Same Day | F61: CUST-1068 | G61: Arjun Das | H61: Corporate | I61: India | J61: Thiruvananthapuram | K61: Kerala | L61: South | M61: 400001 | N61: P-838 | O61: Clothing | P61: Shoes | Q61: Running Shoes | R61: 7328.85 | S61: 3 | T61: 0.25 | U61: 525.68
A62: 1261 | B62: ORD-2024-00261 | C62: 45638 | D62: 45642 | E62: Same Day | F62: CUST-1019 | G62: Diya Mathew | H62: Consumer | I62: India | J62: Thiruvananthapuram | K62: Kerala | L62: North | M62: 400001 | N62: P-524 | O62: Electronics | P62: Accessories | Q62: HP Wireless Keyboard | R62: 3288.8 | S62: 2 | T62: 0.1 | U62: 139.18
A63: 1082 | B63: ORD-2024-00082 | C63: 45389 | D63: 45394 | E63: Second Class | F63: CUST-1111 | G63: Ananya Menon | H63: Consumer | I63: India | J63: Ahmedabad | K63: Gujarat | L63: North | M63: 110001 | N63: P-908 | O63: Office supplies | P63: Paper | Q63: A4 Copier Paper | R63: 1034.13 | S63: 3 | T63: 0.25 | U63: 39.47
A64: 1032 | B64: ORD-2024-00032 | C64: 45512 | D64: 45514 | E64: Standard Class | F64: CUST-1040 | G64: Meera Joseph | H64: Consumer | I64: India | J64: Thiruvananthapuram | K64: Kerala | L64: South | M64: 695001 | N64: P-315 | O64: Office Supplies | P64: Binders | Q64: Office Binder Pack | R64: 1299.96 | S64: 2 | T64: 0.05 | U64: 202.15
A65: 1628 | B65: ORD-2024-00628 | C65: 45405 | D65: 45407 | E65: Second Class | F65: CUST-1089 | G65: Fathima Ali | H65: consumer | I65: India | J65: Bhubaneswar | K65: Odisha | L65: North | M65: 682001 | N65: P-314 | O65: Furniture | P65: Tables | Q65: Study Table | R65: 14827.54 | S65: 2 | T65: 0 | U65: 2289.74
A66: 1432 | B66: ORD-2024-00432 | C66: 45412 | D66: 45418 | E66: Second Class | F66: CUST-1112 | G66: Arjun Das | H66: Home Office | I66: India | J66: Lucknow | K66: Uttar Pradesh | L66: West | M66: 682001 | N66: P-307 | O66: Home Appliances | P66: Kitchen | Q66: Mixer Grinder | R66: 15721.11 | S66: 3 | T66: 0.1 | U66: 991.61
... A71: 1297 | B71: ORD-2024-00297 | C71: 45303 | D71: 45304 | E71: Second Class | F71: CUST-1116 | G71: Adil Khan | H71: corporate | I71: India | J71: Lucknow | K71: Uttar Pradesh | L71: East | M71: 110001 | N71: P-231 | O71: Electronics | P71: Mobiles | Q71: Samsung Galaxy A55 | R71: 68335.26 | S71: 2 | T71: 0 | U71: 6936.83
A72: 1066 | B72: ORD-2024-00066 | C72: 45649 | D72: 45651 | E72: Same Day | F72: CUST-1014 | G72: Riya Paul | H72: Consumer | I72: India | J72: Delhi | K72: Delhi | L72: SOUTH | M72: 600001 | N72: P-391 | O72: Electronics | P72: Accessories | Q72: Logitech Wireless Mouse | R72: 999999.99 | S72: 8 | T72: 0.15 | U72: 86.67
A73: 1507 | B73: ORD-2024-00507 | C73: 45493 | D73: 45497 | E73: First Class | F73: CUST-1058 | G73: Aarav Nair | H73: Consumer | I73: India | J73: Delhi | K73: Delhi | L73: West | M73: 560001 | N73: P-704 | O73: Electronics | P73: Mobiles | Q73: Samsung Galaxy A55 | R73: 109889.68 | S73: 3 | T73: 0.05 | U73: 6555.23
A74: 1491 | B74: ORD-2024-00491 | C74: 45326 | D74: 45330 | E74: First Class | F74: CUST-1085 | G74: Riya Paul | H74: Corporate | I74: India | J74: Bhubaneswar | K74: Odisha | L74: North | M74: 110001 | N74: P-210 | O74: Clothing | P74: Shirts | Q74: Cotton Casual Shirt | R74: 1362.87 | S74: 1 | T74: 0 | U74: 386.87
A75: 1197 | B75: ORD-2024-00197 | C75: 45602 | D75: 45605 | E75: Same Day | F75: CUST-1090 | G75: Vishnu Raj | H75: Home Office | I75: India | J75: Bengaluru | K75: Karnataka | L75: East | M75: 110001 | N75: P-650 | O75: Electronics | P75: Accessories | Q75: HP Wireless Keyboard | R75: 3702.6 | S75: 3 | T75: 0.3 | U75: -358.22
A76: 1463 | B76: ORD-2024-00463 | C76: 45322 | D76: 45325 | E76: Second Class | F76: CUST-1090 | G76: Vishnu Raj | H76: home office | I76: India | J76: Mumbai | K76: Maharashtra | L76: South | M76: 682001 | N76: P-599 | O76: Home appliances | P76: Kitchen | Q76: Mixer Grinder | R76: 22922.39 | S76: 4 | T76: 0 | U76: 2268.41
A77: 1266 | B77: ORD-2024-00266 | C77: 45432 | D77: 45433 | E77: First Class | F77: CUST-1033 | G77: Ananya Menon | H77: Consumer | I77: India | J77: Kolkata | K77: West Bengal | L77: North | M77: 400001 | N77: P-764 | O77: Home Appliances | P77: Kitchen | Q77: Mixer Grinder | R77: 17357.56 | S77: 3 | T77: 0.05 | U77: 2115.21
A78: 1450 | B78: ORD-2024-00450 | C78: 45560 | D78: 45566 | E78: First Class | F78: CUST-1117 | G78: Meera Joseph | H78: Corporate | I78: India | J78: Ahmedabad | K78: Gujarat | L78: East | M78: 600001 | N78: P-332 | O78: Office Supplies | P78: Art | Q78: Marker Set | R78: 1576.76 | S78: 6 | T78: 0.25 | U78: 46.87
A79: 1228 | B79: ORD-2024-00228 | C79: 45548 | D79: 45554 | E79: First Class | F79: CUST-1007 | G79: Ananya Menon | H79: Corporate | I79: India | J79: Mumbai | K79: Maharashtra | L79: East | M79: 682001 | N79: P-958 | O79: Furniture | P79: Bookcases | Q79: Wooden Bookshelf | R79: 6001.87 | S79: 1 | T79: 0 | U79: 956.76
A80: 1165 | B80: ORD-2024-00165 | D80: 45518 | E80: Standard Class | F80: CUST-1107 | G80: Ananya Menon | H80: corporate | I80: India | J80: Hyderabad | K80: Telangana | L80: West | M80: 695001 | N80: P-268 | O80: Clothing | P80: Shoes | Q80: Running Shoes | R80: 9002.68 | S80: 3 | T80: 0.05 | U80: 1711.1
A81: 1077 | B81: ORD-2024-00077 | C81: 45573 | D81: 45574 | E81: Same Day | F81: CUST-1012 | G81: Meera Joseph | H81: Corporate | I81: India | J81: Mumbai | K81: Maharashtra | L81: north | M81: 695001 | N81: P-218 | O81: Furniture | P81: Bookcases | Q81: Wooden Bookshelf | R81: 9054.56 | S81: 2 | T81: 0.25 | U81: -22.52
A82: 1742 | B82: ORD-2024-00742 | C82: 45626 | D82: 45628 | E82: Standard Class | F82: CUST-1008 | G82: Muhammed Shafi | H82: Corporate | I82: India | J82: Kozhikode | K82: Kerala | L82: East | M82: 695001 | N82: P-712 | O82: electronics | P82: Laptops | Q82: Dell Inspiron 15 | R82: 311602.39 | T82: 0.15 | U82: 2932.49
A83: 1073 | B83: ORD-2024-00073 | C83: 45516 | D83: 45517 | E83: Same Day | F83: CUST-1089 | G83: Arjun Das | H83: Consumer | I83: India | J83: Kochi | K83: Kerala | L83: East | M83: 695001 | N83: P-612 | O83: Electronics | P83: Laptops | Q83: Dell Inspiron 15 | R83: 85356.78 | S83: 2 | T83: 0.15 | U83: 819.9
A84: 1300 | B84: ORD-2024-00300 | C84: 45502 | D84: 45507 | E84: Same Day | F84: CUST-1008 | G84: Ananya Menon | H84: Corporate | I84: India | J84: Jaipur | K84: Rajasthan | L84: north | M84: 560001 | N84: P-240 | O84: Office Supplies | P84: Storage | Q84: Document Organizer | R84: 1896.78 | S84: 3 | T84: 0.3 | U84: 7.31
A85: 1653 | B85: ORD-2024-00653 | C85: 45513 | D85: 45519 | E85: First Class | F85: CUST-1026 | G85: Amal Thomas | H85: Consumer | I85: India | J85: Mumbai | K85: Maharashtra | L85: East | M85: 695001 | N85: P-739 | O85: Clothing | P85: Shoes | Q85: Running Shoes | R85: 14054.92 | S85: 5 | T85: 0.15 | U85: 2540.94
A86: 1370 | B86: ORD-2024-00370 | C86: 45346 | D86: 45349 | E86: Second Class | F86: CUST-1025 | G86: Ananya Menon | H86: Consumer | I86: India | J86: Kozhikode | K86: Kerala | L86: East | M86: 682001 | N86: P-568 | O86: home appliances | P86: Kitchen | Q86: Mixer Grinder | R86: 4307.64 | S86: 1 | T86: 0.25 | U86: -131.38
A87: 1064 | B87: ORD-2024-00064 | C87: 45453 | D87: 45454 | E87: Second Class | F87: CUST-1025 | G87: Fathima Ali | H87: CONSUMER | I87: India | J87: Ahmedabad | K87: Gujarat | L87: East | M87: 695001 | N87: P-841 | O87: Furniture | P87: Chairs | Q87: Ergonomic Office Chair | R87: 8039.25 | S87: 1 | T87: 0.1 | U87: 901.48
A88: 1650 | B88: ORD-2024-00650 | C88: 45542 | D88: 45543 | E88: Second Class | F88: CUST-1044 | G88: Sneha Nair | H88: Corporate | I88: India | J88: Mumbai | K88: Maharashtra | L88: North | M88: 682001 | N88: P-729 | O88: Furniture | P88: Bookcases | Q88: Wooden Bookshelf | R88: 13079.41 | S88: 2 | T88: 0 | U88: 2308.75
A89: 1466 | B89: ORD-2024-00466 | C89: 45327 | D89: 45332 | E89: Second Class | F89: CUST-1058 | G89: Arjun Das | H89: Consumer | I89: India | J89: Mumbai | K89: Maharashtra | L89: North | M89: 600001 | N89: P-475 | O89: Clothing | P89: Shirts | Q89: Cotton Casual Shirt | R89: 6266.27 | S89: 5 | T89: 0.05 | U89: 1591.15
A90: 1050 | B90: ORD-2024-00050 | C90: 45567 | D90: 45573 | E90: Second Class | F90: CUST-1063 | G90: Fathima Ali | H90: Corporate | I90: India | J90: Mumbai | K90: Maharashtra | L90: North | M90: 560001 | N90: P-597 | O90: Furniture | P90: Chairs | Q90: Ergonomic Office Chair | R90: 29454.64 | S90: 5 | T90: 0.25 | U90: -59.2
A91: 1363 | B91: ORD-2024-00363 | C91: 45634 | D91: 45637 | E91: Standard Class | F91: CUST-1056 | G91: Adil Khan | H91: Home Office | I91: India | J91: Kozhikode | K91: Kerala | L91: West | M91: 560001 | N91: P-454 | O91: Clothing | P91: Shirts | Q91: Cotton Casual Shirt | R91: 3825.04 | S91: 3 | T91: 0.1 | U91: 828.58
A92: 1193 | B92: ORD-2024-00193 | C92: 45464 | D92: 45467 | E92: Second Class | F92: CUST-1023 | G92: Diya Mathew | H92: corporate | I92: India | J92: Kolkata | K92: West Bengal | L92: East | M92: 110001 | N92: P-537 | O92: Office Supplies | P92: Paper | Q92: A4 Copier Paper | R92: 1867.7 | S92: 4 | T92: 0 | U92: 430.22
A93: 1102 | B93: ORD-2024-00102 | C93: 45592 | D93: 45598 | E93: Second Class | F93: CUST-1114 | G93: Amal Thomas | H93: Home Office | I93: India | J93: Mumbai | K93: Maharashtra | L93: South | M93: 110001 | N93: P-601 | O93: Office supplies | P93: Art | Q93: Marker Set | R93: 1078.28 | S93: 4 | T93: 0.25 | U93: 48.49
A94: 1376 | B94: ORD-2024-00376 | C94: 45579 | D94: 45583 | E94: Same Day | F94: CUST-1087 | G94: Nikhil Varma | H94: Consumer | I94: India | J94: Kolkata | K94: West Bengal | L94: north | M94: 110001 | N94: P-532 | O94: Office Supplies | P94: Art | Q94: Marker Set | R94: 285.37 | S94: 1 | T94: 0.2 | U94: 24.37
... A98: 1546 | B98: ORD-2024-00546 | C98: 45307 | D98: 45309 | E98: Same Day | F98: CUST-1090 | G98: Diya Mathew | H98: Home Office | I98: India | J98: Delhi | K98: Delhi | L98: East | M98: 400001 | N98: P-425 | O98: Home Appliances | P98: Kitchen | Q98: Electric Kettle | R98: 2002.47 | S98: 1 | T98: 0.15 | U98: 69.95
A99: 1024 | B99: ORD-2024-00024 | C99: 45321 | D99: 45326 | E99: Standard Class | F99: CUST-1109 | G99: Rahul Kumar | H99: Corporate | I99: India | J99: Kozhikode | K99: Kerala | L99: South | M99: 600001 | N99: P-169 | O99: Electronics | P99: Laptops | Q99: Dell Inspiron 15 | R99: 143,735.29 | S99: 3 | T99: 0.05 | U99: 11251.26
A100: 1623 | B100: ORD-2024-00623 | C100: 45316 | D100: 45319 | E100: First Class | F100: CUST-1068 | G100: Adil Khan | H100: Consumer | I100: India | J100: Mumbai | K100: Maharashtra | L100: South | M100: 600001 | N100: P-298 | O100: Electronics | P100: Accessories | Q100: Logitech Wireless Mouse | R100: 2000.19 | S100: 2 | T100: 0.2 | U100: -42.53
A101: 1222 | B101: ORD-2024-00222 | C101: 45346 | D101: 45347 | E101: Second Class | F101: CUST-1031 | G101: Fathima Ali | H101: Consumer | I101: India | J101: Kolkata | K101: West Bengal | L101: North | M101: 110001 | N101: P-462 | O101: office supplies | P101: Art | Q101: Marker Set | R101: 2476.17 | S101: 7 | T101: 0.05 | U101: 387.93
A102: 1236 | B102: ORD-2024-00236 | C102: 45462 | D102: 45467 | E102: Same Day | F102: CUST-1103 | G102: Riya Paul | H102: Consumer | I102: India | J102: Bengaluru | K102: Karnataka | L102: North | M102: 560001 | N102: P-442 | O102: Office Supplies | P102: Paper | Q102: A4 Copier Paper | R102: 622.31 | S102: 2 | T102: 0.25 | U102: 28.82
A103: 1324 | B103: ORD-2024-00324 | C103: 45596 | D103: 45599 | E103: First Class | F103: CUST-1117 | G103: Nikhil Varma | H103: Home Office | I103: India | J103: Pune | K103: Maharashtra | L103: south | M103: 673001 | N103: P-497 | O103: Electronics | P103: Mobiles | Q103: Samsung Galaxy A55 | R103: 69424.28 | S103: 2 | T103: 0.05 | U103: 5862.2
A104: 1421 | B104: ORD-2024-00421 | C104: 45629 | D104: 45630 | E104: Second Class | F104: CUST-1058 | G104: Asha Krishnan | H104: Corporate | I104: India | J104: Jaipur | K104: Rajasthan | L104: west | M104: 673001 | N104: P-319 | P104: Tables | Q104: Study Table | R104: 12614.26 | S104: 2 | T104: 0.05 | U104: 1739.83
A105: 1307 | B105: ORD-2024-00307 | C105: 45358 | D105: 45361 | E105: Second Class | F105: CUST-1118 | G105: Asha Krishnan | H105: Consumer | I105: India | J105: Kozhikode | K105: Kerala | L105: north | M105: 673001 | N105: P-122 | O105: Office Supplies | P105: Binders | Q105: Office Binder Pack | R105: 1193.94 | S105: 2 | T105: 0.1 | U105: 127.48
A106: 1159 | B106: ORD-2024-00159 | C106: 45585 | D106: 45587 | E106: First Class | F106: CUST-1051 | G106: Meera Joseph | H106: Home Office | I106: India | J106: Lucknow | K106: Uttar Pradesh | L106: North | M106: 682001 | N106: P-216 | O106: Office supplies | P106: Paper | Q106: A4 Copier Paper | R106: 886.89 | S106: 2 | T106: 0 | U106: 148.4
A107: 1119 | B107: ORD-2024-00119 | C107: 45318 | D107: 45320 | E107: Second Class | F107: CUST-1097 | G107: Diya Mathew | H107: Corporate | I107: India | J107: Mumbai | K107: Maharashtra | L107: South | M107: 400001 | N107: P-183 | O107: Furniture | P107: Chairs | Q107: Ergonomic Office Chair | R107: 32807.4 | S107: 4 | T107: 0 | U107: 4000.71
A108: 1087 | B108: ORD-2024-00087 | C108: 45611 | D108: 45617 | E108: Same Day | F108: CUST-1084 | G108: Ananya Menon | H108: Consumer | I108: India | J108: Thiruvananthapuram | K108: Kerala | L108: North | M108: 110001 | N108: P-790 | O108: Electronics | P108: Mobiles | Q108: Samsung Galaxy A55 | R108: 201990.07 | S108: 7 | T108: 0.2 | U108: -3487.35
...

Sheet cleaned data
A1: Row ID | B1: Order ID | C1: Order Date | D1: Ship Date | E1: Ship Mode | F1: Customer ID | G1: Customer Name | H1: Segment | I1: Country | J1: City | K1: State | L1: Region | M1: Postal Code | N1: Product ID | O1: Category | P1: Sub-Category | Q1: Product Name | R1: Sales | S1: Quantity | T1: Discount | U1: Profit | V1: Sales Check | W1: Quantity Check
A2: 1001 | B2: ORD-2024-00001 | C2: 45363 | D2: 45369 | E2: Standard Class | F2: CUST-1087 | G2: NIKHIL VARMA | H2: Consumer | I2: India | J2: Lucknow | K2: Uttar Pradesh | L2: South | M2: 600001 | N2: P-532 | O2: Electronics | P2: Mobiles | Q2: Samsung Galaxy A55 | R2: 63499.23 | S2: 2 | T2: 0.1 | U2: 3501.42 | V2: OK | W2: OK
A3: 1002 | B3: ORD-2024-00002 | C3: 45579 | D3: 45581 | E3: Same Day | F3: CUST-1029 | G3: SNEHA NAIR | H3: Consumer | I3: India | J3: Kozhikode | K3: Kerala | L3: North | M3: 110001 | N3: P-990 | O3: Electronics | P3: Laptops | Q3: Dell Inspiron 15 | R3: 53930.19 | S3: 1 | T3: 0 | U3: 6224.96 | V3: OK | W3: OK
A4: 1003 | B4: ORD-2024-00003 | C4: 45434 | D4: 45436 | E4: Second Class | F4: CUST-1098 | G4: MEERA JOSEPH | H4: Corporate | I4: India | J4: Kozhikode | K4: Kerala | L4: South | M4: 673001 | N4: P-489 | O4: Clothing | P4: Shoes | Q4: Running Shoes | R4: 9676.42 | S4: 4 | T4: 0.2 | U4: 961.45 | V4: OK | W4: OK
A5: 1004 | B5: ORD-2024-00004 | C5: 45527 | D5: 45532 | E5: Standard Class | F5: CUST-1119 | G5: AMAL THOMAS | H5: Corporate | I5: India | J5: Kochi | K5: Kerala | L5: South | M5: 600001 | N5: P-400 | O5: Furniture | P5: Tables | Q5: Study Table | R5: 20072.74 | S5: 3 | T5: 0 | U5: 3799.65 | V5: OK | W5: OK
A6: 1005 | B6: ORD-2024-00005 | C6: 45652 | D6: 45653 | E6: Standard Class | F6: CUST-1085 | G6: FATHIMA ALI | H6: Corporate | I6: India | J6: Hyderabad | K6: Telangana | L6: North | M6: 673001 | N6: P-975 | O6: Office Supplies | P6: Art | Q6: Marker Set | R6: 1737.67 | S6: 5 | T6: 0.1 | U6: 258.99 | V6: OK | W6: OK
A7: 1006 | B7: ORD-2024-00006 | C7: 45375 | D7: 45378 | E7: First Class | F7: CUST-1027 | G7: ADIL KHAN | H7: Consumer | I7: India | J7: Bengaluru | K7: Karnataka | L7: North | M7: 400001 | N7: P-799 | O7: Home Appliances | P7: Kitchen | Q7: Electric Kettle | R7: 3249.99 | S7: 2 | T7: 0.2 | U7: -130 | V7: OK | W7: OK
A8: 1007 | B8: ORD-2024-00007 | C8: 45375 | D8: 45379 | E8: Same Day | F8: CUST-1035 | G8: MUHAMMED SHAFI | H8: Corporate | I8: India | J8: Lucknow | K8: Uttar Pradesh | L8: West | M8: 400001 | N8: P-432 | O8: Electronics | P8: Mobiles | Q8: Samsung Galaxy A55 | R8: 34123.38 | S8: 1 | T8: 0.1 | U8: 1314.69 | V8: OK | W8: OK
A9: 1008 | B9: ORD-2024-00008 | C9: 45453 | D9: 45457 | E9: First Class | F9: CUST-1009 | G9: FATHIMA ALI | H9: Corporate | I9: India | J9: Hyderabad | K9: Telangana | L9: North | M9: 682001 | N9: P-771 | O9: Clothing | P9: Shoes | Q9: Running Shoes | R9: 3037.09 | S9: 1 | T9: 0 | U9: 639.08 | V9: OK | W9: OK
A10: 1009 | B10: ORD-2024-00009 | C10: 45427 | D10: 45429 | E10: Second Class | F10: CUST-1096 | G10: VISHNU RAJ | H10: Home Office | I10: India | J10: Ahmedabad | K10: Gujarat | L10: North | M10: 400001 | N10: P-698 | O10: Furniture | P10: Bookcases | Q10: Wooden Bookshelf | R10: 17668.7 | S10: 3 | T10: 0.05 | U10: 2280.64 | V10: OK | W10: OK
A11: 1010 | B11: ORD-2024-00010 | C11: 45552 | D11: 45556 | E11: Standard Class | F11: CUST-1097 | G11: AARAV NAIR | H11: Corporate | I11: India | J11: Pune | K11: Maharashtra | L11: South | M11: 682001 | N11: P-742 | O11: Home Appliances | P11: Kitchen | Q11: Mixer Grinder | R11: 10900.01 | S11: 2 | T11: 0.05 | U11: 951.82 | V11: OK | W11: OK
A12: 1011 | B12: ORD-2024-00011 | C12: 45487 | D12: 45492 | E12: Same Day | F12: CUST-1068 | G12: ARJUN DAS | H12: Corporate | I12: India | J12: Thiruvananthapuram | K12: Kerala | L12: South | M12: 400001 | N12: P-838 | O12: Clothing | P12: Shoes | Q12: Running Shoes | R12: 7328.85 | S12: 3 | T12: 0.25 | U12: 525.68 | V12: OK | W12: OK
A13: 1012 | B13: ORD-2024-00012 | C13: 45349 | D13: 45352 | E13: Same Day | F13: CUST-1021 | G13: SNEHA NAIR | H13: Home Office | I13: India | J13: Kochi | K13: Kerala | L13: South | M13: 400001 | N13: P-996 | O13: Office Supplies | P13: Art | Q13: Marker Set | R13: 1175.56 | S13: 4 | T13: 0.2 | U13: 76.79 | V13: OK | W13: OK
... A751: 1750 | B751: ORD-2024-00750 | C751: 45295 | D751: 45297 | E751: Same Day | F751: CUST-1015 | G751: RIYA PAUL | H751: Consumer | I751: India | J751: Mumbai | K751: Maharashtra | L751: West | M751: 600001 | N751: P-612 | O751: Electronics | P751: Laptops | Q751: Dell Inspiron 15 | R751: 275399.02 | S751: 6 | T751: 0.1 | U751: 14644.34 | V751: OK | W751: OK

Sheet pivot analysis
A1: Category | B1: Sum of Sales | D1: Region | E1: Sum of Sales | G1: Segment | H1: Sum of Profit | J1: Category | K1: Sum of Quantity | M1: Row Labels | N1: Count of Order ID
A2: Clothing | B2: 757185.97 | D2: East | E2: 4836233.8 | G2: Consumer | H2: 509235.27 | J2: Clothing | K2: 355 | M2: ORD-2024-00001 | N2: 1
A3: Electronics | B3: 13711838 | D3: North | E3: 3972680.5 | G3: Corporate | H3: 293021.4 | J3: Electronics | K3: 600 | M3: ORD-2024-00002 | N3: 1
A4: Furniture | B4: 3314942.6 | D4: South | E4: 4957758.6 | G4: Home Office | H4: 155047.87 | J4: Furniture | K4: 520 | M4: ORD-2024-00003 | N4: 1
A5: Home Appliances | B5: 773774.1 | D5: West | E5: 6127562.8 | G5: Grand Total | H5: 957304.54 | J5: Home Appliances | K5: 206 | M5: ORD-2024-00004 | N5: 1
A6: Office Supplies | B6: 1336494.9 | D6: Grand Total | E6: 19894236 | J6: Office Supplies | K6: 696 | M6: ORD-2024-00005 | N6: 1
A7: Grand Total | B7: 19894236 | J7: Grand Total | K7: 2377 | M7: ORD-2024-00006 | N7: 1
H8: =GETPIVOTDATA("Profit",$G$1) -> 957304.54 | M8: ORD-2024-00007 | N8: 1
K9: =GETPIVOTDATA("Quantity",$J$1) -> 2377 | M9: ORD-2024-00008 | N9: 1
B10: =GETPIVOTDATA("Sales",$A$1) -> 19894236 | M10: ORD-2024-00009 | N10: 1
M11: ORD-2024-00010 | N11: 1
M12: ORD-2024-00011 | N12: 1
M13: ORD-2024-00012 | N13: 1
M14: ORD-2024-00013 | N14: 1
M15: ORD-2024-00014 | N15: 1
M16: ORD-2024-00015 | N16: 1
M17: ORD-2024-00016 | N17: 1
M18: ORD-2024-00017 | N18: 1
M19: ORD-2024-00018 | N19: 1
M20: ORD-2024-00019 | N20: 1
M21: ORD-2024-00020 | N21: 1
M22: ORD-2024-00021 | N22: 1
... M752: Grand Total | N752: 750
N754: =GETPIVOTDATA("Order ID",$M$1) -> 750

Sheet Dashboard

Sheet Retail Domain & KPIs
A1: Retail Business Domain & KPI Definitions
A3: KPI | B3: Formula / Calculation | C3: Business Meaning
A4: Total Sales | B4: SUM(Sales) | C4: Total revenue generated
A5: Total Profit | B5: SUM(Profit) | C5: Total profit earned
A6: Profit Margin | B6: Total Profit / Total Sales | C6: Profit earned as a percentage of sales
A7: Average Order Value (AOV) | B7: Total Sales / Number of Orders | C7: Average sales value per order
A8: Quantity Sold | B8: SUM(Quantity) | C8: Total number of units sold
A10: Analysis | B10: Purpose
A11: Sales by Product Category | B11: Compare revenue across categories
A12: Sales by Region | B12: Compare regional performance
A13: Customer Segment Performance | B13: Compare Consumer, Corporate, etc.
A14: Sales Trend Over Time | B14: Understand sales changes over dates
A15: Discount vs Profit | B15: Understand how discounts affect profitability

Sheet Basic Analysis
A1: Category | B1: Total Sales | D1: Region | E1: Total Sales | G1: Segment | H1: Total Profit | J1: Category | K1: Total Quantity
A2: Electronics | B2: =SUMIF('Raw Data'!O:O,A2,'Raw Data'!R:R) -> 9604965.3 | D2: North | E2: =SUMIF('Raw Data'!L:L,D2,'Raw Data'!R:R) -> 2622001.2 | G2: Consumer | H2: =SUMIF('Raw Data'!H:H,G2,'Raw Data'!U:U) -> 521751.35 | J2: Electronics | K2: =SUMIF('Raw Data'!O:O,J2,'Raw Data'!S:S) -> 500
A3: Clothing | B3: =SUMIF('Raw Data'!O:O,A3,'Raw Data'!R:R) -> 684144.42 | D3: East | E3: =SUMIF('Raw Data'!L:L,D3,'Raw Data'!R:R) -> 4332640.8 | G3: Corporate | H3: =SUMIF('Raw Data'!H:H,G3,'Raw Data'!U:U) -> 256305.35 | J3: Clothing | K3: =SUMIF('Raw Data'!O:O,J3,'Raw Data'!S:S) -> 312
A4: Furniture | B4: =SUMIF('Raw Data'!O:O,A4,'Raw Data'!R:R) -> 2996961 | D4: South | E4: =SUMIF('Raw Data'!L:L,D4,'Raw Data'!R:R) -> 3618500.3 | G4: Home Office | H4: =SUMIF('Raw Data'!H:H,G4,'Raw Data'!U:U) -> 138780.13 | J4: Furniture | K4: =SUMIF('Raw Data'!O:O,J4,'Raw Data'!S:S) -> 472
A5: Office Supplies | B5: =SUMIF('Raw Data'!O:O,A5,'Raw Data'!R:R) -> 293052.82 | D5: West | E5: =SUMIF('Raw Data'!L:L,D5,'Raw Data'!R:R) -> 4295165.5 | J5: Office Supplies | K5: =SUMIF('Raw Data'!O:O,J5,'Raw Data'!S:S) -> 607
A6: Home Appliances | B6: =SUMIF('Raw Data'!O:O,A6,'Raw Data'!R:R) -> 647905.26 | J6: Home Appliances | K6: =SUMIF('Raw Data'!O:O,J6,'Raw Data'!S:S) -> 174
